{
  "1": [
    "instruction,pen,mouse",
    "training,pen,mouse",
    "task,pen,mouse",
    "instruction,pen,touch",
    "training,pen,touch",
    "task,pen,touch",
    "instruction,pen,trackpad",
    "training,pen,trackpad",
    "task,pen,trackpad",
    "instruction,mouse,touch",
    "training,mouse,touch",
    "task,mouse,touch",
    "instruction,mouse,trackpad",
    "training,mouse,trackpad",
    "task,mouse,trackpad",
    "instruction,touch,trackpad",
    "training,touch,trackpad",
    "task,touch,trackpad"
  ],
  "2": [
    "instruction,pen,touch",
    "training,pen,touch",
    "task,pen,touch",
    "instruction,pen,trackpad",
    "training,pen,trackpad",
    "task,pen,trackpad",
    "instruction,mouse,touch",
    "training,mouse,touch",
    "task,mouse,touch",
    "instruction,mouse,trackpad",
    "training,mouse,trackpad",
    "task,mouse,trackpad",
    "instruction,touch,trackpad",
    "training,touch,trackpad",
    "task,touch,trackpad",
    "instruction,pen,mouse",
    "training,pen,mouse",
    "task,pen,mouse"
  ],
  "3": [
    "instruction,pen,trackpad",
    "training,pen,trackpad",
    "task,pen,trackpad",
    "instruction,mouse,touch",
    "training,mouse,touch",
    "task,mouse,touch",
    "instruction,mouse,trackpad",
    "training,mouse,trackpad",
    "task,mouse,trackpad",
    "instruction,touch,trackpad",
    "training,touch,trackpad",
    "task,touch,trackpad",
    "instruction,pen,mouse",
    "training,pen,mouse",
    "task,pen,mouse",
    "instruction,pen,touch",
    "training,pen,touch",
    "task,pen,touch"
  ],
  "4": [
    "instruction,mouse,touch",
    "training,mouse,touch",
    "task,mouse,touch",
    "instruction,mouse,trackpad",
    "training,mouse,trackpad",
    "task,mouse,trackpad",
    "instruction,touch,trackpad",
    "training,touch,trackpad",
    "task,touch,trackpad",
    "instruction,pen,mouse",
    "training,pen,mouse",
    "task,pen,mouse",
    "instruction,pen,touch",
    "training,pen,touch",
    "task,pen,touch",
    "instruction,pen,trackpad",
    "training,pen,trackpad",
    "task,pen,trackpad"
  ],
  "5": [
    "instruction,mouse,trackpad",
    "training,mouse,trackpad",
    "task,mouse,trackpad",
    "instruction,touch,trackpad",
    "training,touch,trackpad",
    "task,touch,trackpad",
    "instruction,pen,mouse",
    "training,pen,mouse",
    "task,pen,mouse",
    "instruction,pen,touch",
    "training,pen,touch",
    "task,pen,touch",
    "instruction,pen,trackpad",
    "training,pen,trackpad",
    "task,pen,trackpad",
    "instruction,mouse,touch",
    "training,mouse,touch",
    "task,mouse,touch"
  ],
  "6": [
    "instruction,touch,trackpad",
    "training,touch,trackpad",
    "task,touch,trackpad",
    "instruction,pen,mouse",
    "training,pen,mouse",
    "task,pen,mouse",
    "instruction,pen,touch",
    "training,pen,touch",
    "task,pen,touch",
    "instruction,pen,trackpad",
    "training,pen,trackpad",
    "task,pen,trackpad",
    "instruction,mouse,touch",
    "training,mouse,touch",
    "task,mouse,touch",
    "instruction,mouse,trackpad",
    "training,mouse,trackpad",
    "task,mouse,trackpad"
  ],
  "7": [
    "instruction,pen,mouse",
    "training,pen,mouse",
    "task,pen,mouse",
    "instruction,pen,touch",
    "training,pen,touch",
    "task,pen,touch",
    "instruction,pen,trackpad",
    "training,pen,trackpad",
    "task,pen,trackpad",
    "instruction,mouse,touch",
    "training,mouse,touch",
    "task,mouse,touch",
    "instruction,mouse,trackpad",
    "training,mouse,trackpad",
    "task,mouse,trackpad",
    "instruction,touch,trackpad",
    "training,touch,trackpad",
    "task,touch,trackpad"
  ],
  "8": [
    "instruction,pen,touch",
    "training,pen,touch",
    "task,pen,touch",
    "instruction,pen,trackpad",
    "training,pen,trackpad",
    "task,pen,trackpad",
    "instruction,mouse,touch",
    "training,mouse,touch",
    "task,mouse,touch",
    "instruction,mouse,trackpad",
    "training,mouse,trackpad",
    "task,mouse,trackpad",
    "instruction,touch,trackpad",
    "training,touch,trackpad",
    "task,touch,trackpad",
    "instruction,pen,mouse",
    "training,pen,mouse",
    "task,pen,mouse"
  ],
  "9": [
    "instruction,pen,trackpad",
    "training,pen,trackpad",
    "task,pen,trackpad",
    "instruction,mouse,touch",
    "training,mouse,touch",
    "task,mouse,touch",
    "instruction,mouse,trackpad",
    "training,mouse,trackpad",
    "task,mouse,trackpad",
    "instruction,touch,trackpad",
    "training,touch,trackpad",
    "task,touch,trackpad",
    "instruction,pen,mouse",
    "training,pen,mouse",
    "task,pen,mouse",
    "instruction,pen,touch",
    "training,pen,touch",
    "task,pen,touch"
  ],
  "10": [
    "instruction,mouse,touch",
    "training,mouse,touch",
    "task,mouse,touch",
    "instruction,mouse,trackpad",
    "training,mouse,trackpad",
    "task,mouse,trackpad",
    "instruction,touch,trackpad",
    "training,touch,trackpad",
    "task,touch,trackpad",
    "instruction,pen,mouse",
    "training,pen,mouse",
    "task,pen,mouse",
    "instruction,pen,touch",
    "training,pen,touch",
    "task,pen,touch",
    "instruction,pen,trackpad",
    "training,pen,trackpad",
    "task,pen,trackpad"
  ],
  "11": [
    "instruction,mouse,trackpad",
    "training,mouse,trackpad",
    "task,mouse,trackpad",
    "instruction,touch,trackpad",
    "training,touch,trackpad",
    "task,touch,trackpad",
    "instruction,pen,mouse",
    "training,pen,mouse",
    "task,pen,mouse",
    "instruction,pen,touch",
    "training,pen,touch",
    "task,pen,touch",
    "instruction,pen,trackpad",
    "training,pen,trackpad",
    "task,pen,trackpad",
    "instruction,mouse,touch",
    "training,mouse,touch",
    "task,mouse,touch"
  ],
  "12": [
    "instruction,touch,trackpad",
    "training,touch,trackpad",
    "task,touch,trackpad",
    "instruction,pen,mouse",
    "training,pen,mouse",
    "task,pen,mouse",
    "instruction,pen,touch",
    "training,pen,touch",
    "task,pen,touch",
    "instruction,pen,trackpad",
    "training,pen,trackpad",
    "task,pen,trackpad",
    "instruction,mouse,touch",
    "training,mouse,touch",
    "task,mouse,touch",
    "instruction,mouse,trackpad",
    "training,mouse,trackpad",
    "task,mouse,trackpad"
  ]
}